{
  "updatedAt": "2026-07-14T06:54:47.305271+00:00",
  "sources": [
    {
      "id": "sumo-association",
      "label": "日本相撲協会",
      "ok": true,
      "count": 3
    },
    {
      "id": "dmenu-docomo",
      "label": "dmenuスポーツ",
      "ok": true,
      "count": 5
    }
  ],
  "items": [
    {
      "id": "dmenu-docomo-20260714084",
      "title": "“史上最強の新弟子”旭富士が無傷２３連勝！元十両に立ち合い動いて制す【大相撲】",
      "url": "https://topics.smt.docomo.ne.jp/article/dailysports/sports/20260714084",
      "publishedAt": "2026-07-14",
      "publishedAtRaw": "デイリースポーツ　7月14日 15時09分",
      "sourceId": "dmenu-docomo",
      "sourceLabel": "dmenuスポーツ"
    },
    {
      "id": "dmenu-docomo-hochi-20260714-OHT1T51147",
      "title": "【大相撲】横綱のしこ名を継ぐ旭富士、歴代単独４位の序ノ口デビューから２３連勝",
      "url": "https://topics.smt.docomo.ne.jp/article/hochi/sports/hochi-20260714-OHT1T51147",
      "publishedAt": "2026-07-14",
      "publishedAtRaw": "スポーツ報知　7月14日 14時59分",
      "sourceId": "dmenu-docomo",
      "sourceLabel": "dmenuスポーツ"
    },
    {
      "id": "dmenu-docomo-hochi-20260714-OHT1T51132",
      "title": "幕下復帰の三田　“イケメン”対決制して連勝発進「強い。しっかり対策した」…隆志戦では幕下屈指の大きな拍手",
      "url": "https://topics.smt.docomo.ne.jp/article/hochi/sports/hochi-20260714-OHT1T51132",
      "publishedAt": "2026-07-14",
      "publishedAtRaw": "スポーツ報知　7月14日 14時38分",
      "sourceId": "dmenu-docomo",
      "sourceLabel": "dmenuスポーツ"
    },
    {
      "id": "dmenu-docomo-hochi-20260714-OHT1T51138",
      "title": "幕下・延原が連敗　「動き自体は悪くない。勝ち負け関係なく思い切りいって、前に出たい」",
      "url": "https://topics.smt.docomo.ne.jp/article/hochi/sports/hochi-20260714-OHT1T51138",
      "publishedAt": "2026-07-14",
      "publishedAtRaw": "スポーツ報知　7月14日 14時38分",
      "sourceId": "dmenu-docomo",
      "sourceLabel": "dmenuスポーツ"
    },
    {
      "id": "dmenu-docomo-nikkangendai-1231767",
      "title": "横綱大の里 初日から連敗でチラつく3場所連続休場…転げ落ちた先の土俵下でア然ボー然",
      "url": "https://topics.smt.docomo.ne.jp/article/nikkangendai/sports/nikkangendai-1231767",
      "publishedAt": "2026-07-14",
      "publishedAtRaw": "日刊ゲンダイDIGITAL　7月14日 13時55分",
      "sourceId": "dmenu-docomo",
      "sourceLabel": "dmenuスポーツ"
    },
    {
      "id": "sumo-association-755",
      "title": "大相撲七月場所「土俵祭」についてのお知らせ",
      "url": "https://www.sumo.or.jp/IrohaKyokaiInformation/detail?id=755",
      "publishedAt": "2026-07-06",
      "publishedAtRaw": "令和8年7月6日",
      "sourceId": "sumo-association",
      "sourceLabel": "日本相撲協会"
    },
    {
      "id": "sumo-association-754",
      "title": "令和8年 第十六回 夏休み!!相撲健康体操 in 国技館",
      "url": "https://www.sumo.or.jp/IrohaKyokaiInformation/detail?id=754",
      "publishedAt": "2026-07-01",
      "publishedAtRaw": "令和8年7月1日",
      "sourceId": "sumo-association",
      "sourceLabel": "日本相撲協会"
    },
    {
      "id": "sumo-association-753",
      "title": "引退のお知らせ",
      "url": "https://www.sumo.or.jp/IrohaKyokaiInformation/detail?id=753",
      "publishedAt": "2026-05-25",
      "publishedAtRaw": "令和8年5月25日",
      "sourceId": "sumo-association",
      "sourceLabel": "日本相撲協会"
    }
  ]
}
