{
  "updatedAt": "2026-07-24T00:48:14.882856+00:00",
  "sources": [
    {
      "id": "sumo-association",
      "label": "日本相撲協会",
      "ok": true,
      "count": 3
    },
    {
      "id": "dmenu-docomo",
      "label": "dmenuスポーツ",
      "ok": true,
      "count": 5
    }
  ],
  "items": [
    {
      "id": "dmenu-docomo-abematimes-10262489",
      "title": "「何なの、このカッコよさ」相撲“未経験”で角界入りした190センチのイケメン力士 驚異のスタイルが話題",
      "url": "https://topics.smt.docomo.ne.jp/article/abematimes/sports/abematimes-10262489",
      "publishedAt": "2026-07-24",
      "publishedAtRaw": "ABEMA TIMES　7月24日 7時44分",
      "sourceId": "dmenu-docomo",
      "sourceLabel": "dmenuスポーツ"
    },
    {
      "id": "dmenu-docomo-abematimes-10262488",
      "title": "「高安おこ」「高安の夢が…」尊富士が立ち合いで…高安が土俵下で見せた“表情”が印象的 ファン落胆 「立ち合い当たってから見たかった」天鎧鵬も困惑",
      "url": "https://topics.smt.docomo.ne.jp/article/abematimes/sports/abematimes-10262488",
      "publishedAt": "2026-07-24",
      "publishedAtRaw": "ABEMA TIMES　7月24日 7時01分",
      "sourceId": "dmenu-docomo",
      "sourceLabel": "dmenuスポーツ"
    },
    {
      "id": "dmenu-docomo-sanspo-_sports_sumo_S2BJGYJLGRECRJIZYHDBXPADG4",
      "title": "舞の海氏「表情に出さないのがまた力士らしくていい」／名古屋場所",
      "url": "https://topics.smt.docomo.ne.jp/article/sanspo/sports/sanspo-_sports_sumo_S2BJGYJLGRECRJIZYHDBXPADG4",
      "publishedAt": "2026-07-24",
      "publishedAtRaw": "SANSPO　7月24日 7時00分",
      "sourceId": "dmenu-docomo",
      "sourceLabel": "dmenuスポーツ"
    },
    {
      "id": "dmenu-docomo-sanspo-_sports_sumo_W4FRTYXOZBB4PIRGYR7CSV233Y",
      "title": "元貴景勝「本人の回復力次第だと思うんですけど幕内でやっていくには…」／名古屋場所",
      "url": "https://topics.smt.docomo.ne.jp/article/sanspo/sports/sanspo-_sports_sumo_W4FRTYXOZBB4PIRGYR7CSV233Y",
      "publishedAt": "2026-07-24",
      "publishedAtRaw": "SANSPO　7月24日 6時30分",
      "sourceId": "dmenu-docomo",
      "sourceLabel": "dmenuスポーツ"
    },
    {
      "id": "dmenu-docomo-20260724034",
      "title": "【解説】霧島は流れで腕をたぐれた　大の里は「全然、気持ちが見えなかったのが残念」",
      "url": "https://topics.smt.docomo.ne.jp/article/dailysports/sports/20260724034",
      "publishedAt": "2026-07-24",
      "publishedAtRaw": "デイリースポーツ　7月24日 6時00分",
      "sourceId": "dmenu-docomo",
      "sourceLabel": "dmenuスポーツ"
    },
    {
      "id": "sumo-association-755",
      "title": "大相撲七月場所「土俵祭」についてのお知らせ",
      "url": "https://www.sumo.or.jp/IrohaKyokaiInformation/detail?id=755",
      "publishedAt": "2026-07-06",
      "publishedAtRaw": "令和8年7月6日",
      "sourceId": "sumo-association",
      "sourceLabel": "日本相撲協会"
    },
    {
      "id": "sumo-association-754",
      "title": "令和8年 第十六回 夏休み!!相撲健康体操 in 国技館",
      "url": "https://www.sumo.or.jp/IrohaKyokaiInformation/detail?id=754",
      "publishedAt": "2026-07-01",
      "publishedAtRaw": "令和8年7月1日",
      "sourceId": "sumo-association",
      "sourceLabel": "日本相撲協会"
    },
    {
      "id": "sumo-association-753",
      "title": "引退のお知らせ",
      "url": "https://www.sumo.or.jp/IrohaKyokaiInformation/detail?id=753",
      "publishedAt": "2026-05-25",
      "publishedAtRaw": "令和8年5月25日",
      "sourceId": "sumo-association",
      "sourceLabel": "日本相撲協会"
    }
  ]
}
